src/docstringFormatter/__init__.py
src/docstringFormatter/_version.py
src/docstringFormatter/docstringFormatter.py
docstringFormatter-1.0.0.dist-info/LICENSE
docstringFormatter-1.0.0.dist-info/METADATA
docstringFormatter-1.0.0.dist-info/WHEEL
docstringFormatter-1.0.0.dist-info/top_level.txt
docstringFormatter-1.0.0.dist-info/RECORD
