Metadata-Version: 2.1
Name: docstringFormatter
Version: 1.0.0
Summary: Format docstring to be able to entry in DeepL or GoogleTranslate
Author-email: Aoi Natsuki <blautinte8@gmail.com>
Maintainer-email: Blau Tinte <blautinte8@gmail.com>
License: Copyright (c) 2023 Aoi Natsuki
Project-URL: Homepage, https://github.com/NatsuSolar/docstringFormatter
Project-URL: Documentation, https://github.com/NatsuSolar/docstringFormatter/blob/main/README.md
Project-URL: Repository, https://github.com/NatsuSolar/docstringFormatter
Project-URL: Changelog, https://github.com/NatsuSolar/docstringFormatter/blob/main/CHANGELOG.md
Project-URL: Bug_Tracker, https://github.com/NatsuSolar/docstringFormatter/issues
Keywords: docstringFormatter,docstring,formatter,DeepL,GoogleTranslate,delete,remove,indent,newline,tab,space,replace
Classifier: Programming Language :: Python :: 3.11
Classifier: Development Status :: 3 - Alpha
Classifier: License :: OSI Approved :: MIT License
Classifier: Framework :: Flake8
Classifier: Natural Language :: English
Classifier: Operating System :: Microsoft :: Windows
Classifier: Programming Language :: Python :: 3.11
Classifier: Intended Audience :: Developers
Classifier: Topic :: Software Development :: Documentation
Requires-Python: >=3.7
License-File: LICENSE
